[
  {
    "type": "section",
    "text": {
      "type": "mrkdwn",
      "text": "New version published (0.1.$CIRCLE_BUILD_NUM) - TEST"
    }
  },
  {
    "type": "section",
    "fields": [
      {
        "type": "mrkdwn",
        "text": "*Mac:*\nhttps://physio-client-2.s3.eu-central-1.amazonaws.com/Physio+Client+2-0.1.$CIRCLE_BUILD_NUM.dmg"
      },
      {
        "type": "mrkdwn",
        "text": "*Windows:*\nhttps://physio-client-2.s3.eu-central-1.amazonaws.com/Physio+Client+2+Setup+-0.1.$CIRCLE_BUILD_NUM.exe"
      }
    ]
  }
]
